{
  "result": "OK",
  "video": {
    "id": "v34",
    "playlist": [
      {
        "file": "https://d2klya0a52nzxz.cloudfront.net/2016/08/18/hls1080k/01c00381b6727394701e731761f37f6838cbc767aa68d5d46abac4157ac6e791.mp4",
        "mediaid": "d2klya0a52nzxz.cloudfront.net/2016/08/18/hls1080k/01c00381b6727394701e731761f37f6838cbc767aa68d5d46abac4157ac6e791.mp4"
      }
    ],
    "date": "Nov 16 2016 4:37:24 pm",
    "genre": "Bluze",
    "title": "Alilua",
    "viewers": 848,
    "preview": "assets/vid_thumb.jpg",
    "donations": 4945,
    "injii_donations": 356,
    "top_supporters": [
      {
        "id": "u2",
        "avatar": null,
        "firstname": null,
        "lastname": null,
        "stars": 256,
        "donated": 400
      },
      {
        "id": "u2",
        "avatar": "https://ipsumimage.appspot.com/100",
        "firstname": "Joe",
        "lastname": "Smith",
        "stars": 356,
        "donated": 390
      },
      {
        "id": "u2",
        "avatar": "https://ipsumimage.appspot.com/100",
        "firstname": "Grag",
        "lastname": "Oregful",
        "stars": 356,
        "donated": 280
      }
    ]
  },
  "charity": {
    "id": "c1",
    "username": "labore",
    "charityname": "MrcharityName",
    "firstname": "Will",
    "lastname": "Willis",
    "state": "NY",
    "city": "Aklahoma",
    "country": "Germaby",
    "avatar": "https://ipsumimage.appspot.com/100",
    "bio": "Lorem ipsum dolor sit amet, consectetur adipisicing elit. Ipsa, veritatis!",
    "donations": 477,
    "homeUrl": null,
    "EIN": null,
    "email": "gotechto@gmail.com",
    "social": [
      {
        "type": "facebook",
        "link": "https://www.facebook.com/profile",
        "pattern": "https://www.facebook.com/",
        "image": "../../assets/svg/icons/facebook-logo-button.svg"
      },
      {
        "type": "twitter",
        "link": "https://twitter.com/profile",
        "pattern": "https://twitter.com/",
        "image": "../../assets/svg/icons/twitter-logo-button.svg"
      },
      {
        "type": "instagram",
        "link": "https://www.instagram.com/45",
        "pattern": "https://www.instagram.com/",
        "image": "../../assets/svg/icons/instagram-logo.svg"
      },
      {
        "type": "google",
        "link": null,
        "pattern": "https://plus.google.com/",
        "image": "../../assets/svg/icons/google-plus.svg"
      }
    ],
    "top_supporters": [
      {
        "id": "u2",
        "avatar": "https://ipsumimage.appspot.com/100",
        "firstname": "Apls",
        "lastname": "Uitjer",
        "stars": 356,
        "donated": 560
      },
      {
        "id": "u2",
        "avatar": "https://ipsumimage.appspot.com/100",
        "firstname": "Goran",
        "lastname": "Swift",
        "stars": 356,
        "donated": 458
      },
      {
        "id": "u2",
        "avatar": null,
        "firstname": null,
        "lastname": null,
        "stars": 256,
        "donated": 400
      }
    ]
  },
  "artist": {
    "id": "a1",
    "username": "willBallads",
    "rating": 6,
    "band": "WilGroup",
    "firstname": "Jason",
    "lastname": "Ommond",
    "state": "Alaska",
    "city": "Sidney",
    "birth": "1900-00-00",
    "phone": "+10055550000",
    "country": "Australia",
    "avatar": "https://ipsumimage.appspot.com/100",
    "bio": "Lorem ipsum dolor sit amet, consectetur adipisicing elit. Ipsa, veritatis! Ipsum dolor sit amet, consectetur adipisicing elit",
    "genre": "rock",
    "stars": 547,
    "stats": {
      "donations": 6789,
      "injii_donations": 567
    },
    "portfolio": [
      {
        "type": "bandcamp",
        "link": "//bandcamp.com/qwerty",
        "pattern": "https://bandcamp.com/",
        "image": "../../assets/svg/icons/bandcamp-logo.svg"
      },
      {
        "type": "soundcloud",
        "link": "https://soundcloud.com/346",
        "pattern": "https://soundcloud.com/",
        "image": "../../assets/svg/icons/soundcloud-logo.svg"
      },
      {
        "type": "reverbnation",
        "link": "https://www.reverbnation.com/ghj",
        "pattern": "https://www.reverbnation.com/",
        "image": "../../assets/svg/icons/reverbnation-logo.svg"
      },
      {
        "type": "youtube",
        "link": "https://www.youtube.com/jrty/g",
        "pattern": "https://www.youtube.com/",
        "image": "../../assets/svg/icons/youtube-logo.svg"
      },
      {
        "type": "itunes",
        "link": "https://itunes.apple.com/",
        "pattern": "https://itunes.apple.com/",
        "image": "../../assets/svg/icons/itunes-logo.svg"
      }
    ],
    "social": [
      {
        "type": "facebook",
        "link": "https://www.facebook.com/profile",
        "pattern": "https://www.facebook.com/",
        "image": "../../assets/svg/icons/facebook-logo-button.svg"
      },
      {
        "type": "twitter",
        "link": "https://twitter.com/profile",
        "pattern": "https://twitter.com/",
        "image": "../../assets/svg/icons/twitter-logo-button.svg"
      },
      {
        "type": "instagram",
        "link": "https://www.instagram.com/45",
        "pattern": "https://www.instagram.com/",
        "image": "../../assets/svg/icons/instagram-logo.svg"
      },
      {
        "type": "google",
        "link": null,
        "pattern": "https://plus.google.com/",
        "image": "../../assets/svg/icons/google-plus.svg"
      }
    ]
  }
}